fusion_stat/__init__.py
fusion_stat/api.py
fusion_stat/config.py
fusion_stat/models.py
fusion_stat/py.typed
fusion_stat/scraper.py
fusion_stat/spiders/__init__.py
fusion_stat/spiders/fbref/__init__.py
fusion_stat/spiders/fbref/_common.py
fusion_stat/spiders/fbref/competition.py
fusion_stat/spiders/fbref/competitions.py
fusion_stat/spiders/fbref/match.py
fusion_stat/spiders/fbref/matches.py
fusion_stat/spiders/fbref/player.py
fusion_stat/spiders/fbref/team.py
fusion_stat/spiders/fotmob/__init__.py
fusion_stat/spiders/fotmob/_common.py
fusion_stat/spiders/fotmob/competition.py
fusion_stat/spiders/fotmob/competitions.py
fusion_stat/spiders/fotmob/match.py
fusion_stat/spiders/fotmob/matches.py
fusion_stat/spiders/fotmob/player.py
fusion_stat/spiders/fotmob/staff.py
fusion_stat/spiders/fotmob/team.py
fusion_stat/spiders/official/__init__.py
fusion_stat/spiders/official/_common.py
fusion_stat/spiders/official/competition.py
fusion_stat/spiders/official/competitions.py
fusion_stat/spiders/transfermarkt/__init__.py
fusion_stat/spiders/transfermarkt/_common.py
fusion_stat/spiders/transfermarkt/competition.py
fusion_stat/spiders/transfermarkt/competitions.py
fusion_stat/spiders/transfermarkt/player.py
fusion_stat/spiders/transfermarkt/staff.py
fusion_stat/spiders/transfermarkt/staffs.py
fusion_stat/spiders/transfermarkt/team.py
fusion_stat/utils.py
fusion_stat-0.0.11.dist-info/LICENSE
fusion_stat-0.0.11.dist-info/METADATA
fusion_stat-0.0.11.dist-info/WHEEL
fusion_stat-0.0.11.dist-info/RECORD
