Metadata-Version: 2.1
Name: fusion-stat
Version: 0.0.11
Summary: Scrape football data from multiple sources simultaneously.
Home-page: https://github.com/tanzhijian/fusion-stat
License: MIT
Author: tanzhijian
Author-email: tanzhijianorg@outlook.com
Requires-Python: >=3.10
Classifier: License :: OSI Approved :: MIT License
Classifier: Programming Language :: Python :: 3
Classifier: Programming Language :: Python :: 3.10
Classifier: Programming Language :: Python :: 3.11
Classifier: Programming Language :: Python :: 3.12
Requires-Dist: fifacodes (>=0.1.4,<0.2.0)
Requires-Dist: httpx (>=0.27.0,<0.28.0)
Requires-Dist: parsel (>=1.9.0,<2.0.0)
Requires-Dist: pydantic (>=2.6.4,<3.0.0)
Requires-Dist: rapidfuzz (>=3.6.2,<4.0.0)
Project-URL: Repository, https://github.com/tanzhijian/fusion-stat
